vfscript/__init__.py
vfscript/config.py
vfscript/config_loader.py
vfscript/core.py
vfscript/params.py
vfscript/vfs.py
vfscript/vfs_win.py
vfscript/cluster_processing/__init__.py
vfscript/cluster_processing/cluster_macth.py
vfscript/cluster_processing/cluster_processor.py
vfscript/cluster_processing/cluster_processor_machine.py
vfscript/cluster_processing/export_cluster_list.py
vfscript/cluster_processing/key_files_separator.py
vfscript/predictors/__init__.py
vfscript/predictors/coeff_vacancy.py
vfscript/predictors/mach_finger.py
vfscript/predictors/math_finger.py
vfscript/predictors/vacancy_predictors.py
vfscript/predictors/vacancy_predictors_classified.py
vfscript/runner/__init__.py
vfscript/runner/deformation_analyzer.py
vfscript/runner/finger_runner.py
vfscript/runner/vacancy_runner.py
vfscript/runner/ws_predictor.py
vfscript/surface_processor/__init__.py
vfscript/surface_processor/cluster_dump_processor.py
vfscript/surface_processor/surface_processor.py
vfscript/training/__init__.py
vfscript/training/cristal_structure_gen.py
vfscript/training/synthetic_data.py
vfscript/training/training_btr_assing.py
vfscript/training/training_btree.py
vfscript/training/training_defect_fingerstyle.py
vfscript/training/training_fingerstyle.py
vfscript/training/training_graph.py
vfscript/training/training_processor.py
vfscript/training/training_surface.py
vfscript/training/utils.py
vfscript/training/vacancy_predictor_curve.py
vfscript/training/vacancy_predictor_graph.py
vfscript/training/vacancy_predictors.py
vfscript/training/vacancy_predictors_classified.py
vfscript/utils/__init__.py
vfscript/utils/io_utils.py
vfscript/utils/utilidades_clustering.py
vacancycalculator-0.5.3.5.dist-info/METADATA
vacancycalculator-0.5.3.5.dist-info/WHEEL
vacancycalculator-0.5.3.5.dist-info/entry_points.txt
vacancycalculator-0.5.3.5.dist-info/top_level.txt
vacancycalculator-0.5.3.5.dist-info/RECORD
